MANIFEST.in
README.md
setup.cfg
setup.py
src/hub_pip/BlackDuckConfig.py
src/hub_pip/BlackDuckCore.py
src/hub_pip/BlackDuckPackage.py
src/hub_pip/BlackDuckPlugin.py
src/hub_pip/BlackDuckSerializer.py
src/hub_pip/FileHandler.py
src/hub_pip/LogHandler.py
src/hub_pip/Main.py
src/hub_pip/TreeHandler.py
src/hub_pip/__init__.py
src/hub_pip.egg-info/PKG-INFO
src/hub_pip.egg-info/SOURCES.txt
src/hub_pip.egg-info/dependency_links.txt
src/hub_pip.egg-info/entry_points.txt
src/hub_pip.egg-info/requires.txt
src/hub_pip.egg-info/top_level.txt
src/hub_pip/api/AuthenticationDataService.py
src/hub_pip/api/CodeLocationsDataService.py
src/hub_pip/api/HubServerConfig.py
src/hub_pip/api/LinkedDataDataService.py
src/hub_pip/api/ProjectDataService.py
src/hub_pip/api/RestConnection.py
src/hub_pip/api/ScanSummaryDataService.py
src/hub_pip/api/VersionBomPolicyDataService.py
src/hub_pip/api/WaitingDataService.py
src/hub_pip/api/__init__.py
src/hub_pip/api/model/CodeLocationView.py
src/hub_pip/api/model/MetadataView.py
src/hub_pip/api/model/NameValuePair.py
src/hub_pip/api/model/PagedCodeLocationView.py
src/hub_pip/api/model/PagedProjectVersionView.py
src/hub_pip/api/model/PagedProjectView.py
src/hub_pip/api/model/PagedScanSummaryView.py
src/hub_pip/api/model/ProjectVersionView.py
src/hub_pip/api/model/ProjectView.py
src/hub_pip/api/model/ScanSummaryView.py
src/hub_pip/api/model/VersionBomPolicyStatusView.py
src/hub_pip/api/model/__init__.py
src/hub_pip/bdio/Bdio.py
src/hub_pip/bdio/BdioComponent.py
src/hub_pip/bdio/BdioExternalIdentifier.py
src/hub_pip/bdio/BdioProject.py
src/hub_pip/bdio/BdioRelationship.py
src/hub_pip/bdio/BillOfMaterials.py
src/hub_pip/bdio/__init__.py
src/hub_pip/tests/__init__.py
src/hub_pip/tests/helper.py
src/hub_pip/tests/test_bdio.py
src/hub_pip/tests/test_config.py
src/hub_pip/tests/test_flat_list.py
src/hub_pip/tests/test_tree.py