Metadata-Version: 1.0
Name: hub-pip
Version: 1.0.0
Summary: Generates and deploys Black Duck I/O files for use with the Black Duck Hub
Home-page: https://github.com/blackducksoftware/hub-pip
Author: Black Duck Software
Author-email: bdsoss@blackducksoftware.com
License: Apache 2.0
Keywords: hub-pip blackduck
Platform: UNKNOWN
